MANIFEST.in
README.md
setup.cfg
setup.py
pyspark/__init__.py
pyspark/_globals.py
pyspark/_typing.pyi
pyspark/accumulators.py
pyspark/conf.py
pyspark/daemon.py
pyspark/errors_doc_gen.py
pyspark/find_spark_home.py
pyspark/install.py
pyspark/instrumentation_utils.py
pyspark/java_gateway.py
pyspark/join.py
pyspark/loose_version.py
pyspark/profiler.py
pyspark/py.typed
pyspark/rddsampler.py
pyspark/resultiterable.py
pyspark/serializers.py
pyspark/shell.py
pyspark/shuffle.py
pyspark/statcounter.py
pyspark/storagelevel.py
pyspark/taskcontext.py
pyspark/traceback_utils.py
pyspark/util.py
pyspark/version.py
pyspark/worker.py
pyspark/worker_util.py
pyspark/cloudpickle/__init__.py
pyspark/cloudpickle/cloudpickle.py
pyspark/cloudpickle/cloudpickle_fast.py
pyspark/cloudpickle/compat.py
pyspark/errors/__init__.py
pyspark/errors/error-conditions.json
pyspark/errors/error_classes.py
pyspark/errors/utils.py
pyspark/errors/exceptions/__init__.py
pyspark/errors/exceptions/base.py
pyspark/errors/exceptions/captured.py
pyspark/errors/exceptions/connect.py
pyspark/logger/__init__.py
pyspark/logger/logger.py
pyspark/ml/__init__.py
pyspark/ml/_typing.pyi
pyspark/ml/base.py
pyspark/ml/classification.py
pyspark/ml/clustering.py
pyspark/ml/common.py
pyspark/ml/dl_util.py
pyspark/ml/evaluation.py
pyspark/ml/feature.py
pyspark/ml/fpm.py
pyspark/ml/functions.py
pyspark/ml/image.py
pyspark/ml/model_cache.py
pyspark/ml/pipeline.py
pyspark/ml/recommendation.py
pyspark/ml/regression.py
pyspark/ml/stat.py
pyspark/ml/tree.py
pyspark/ml/tuning.py
pyspark/ml/util.py
pyspark/ml/wrapper.py
pyspark/ml/connect/__init__.py
pyspark/ml/connect/base.py
pyspark/ml/connect/classification.py
pyspark/ml/connect/evaluation.py
pyspark/ml/connect/feature.py
pyspark/ml/connect/functions.py
pyspark/ml/connect/io_utils.py
pyspark/ml/connect/pipeline.py
pyspark/ml/connect/summarizer.py
pyspark/ml/connect/tuning.py
pyspark/ml/connect/util.py
pyspark/ml/deepspeed/__init__.py
pyspark/ml/deepspeed/deepspeed_distributor.py
pyspark_connect.egg-info/PKG-INFO
pyspark_connect.egg-info/SOURCES.txt
pyspark_connect.egg-info/dependency_links.txt
pyspark_connect.egg-info/requires.txt
pyspark_connect.egg-info/top_level.txt