Metadata-Version: 2.1
Name: pyspark-connect
Version: 4.0.0.dev2
Summary: Python Spark Connect client for Apache Spark
Home-page: https://github.com/apache/spark/tree/master/python
Author: Spark Developers
Author-email: dev@spark.apache.org
License: http://www.apache.org/licenses/LICENSE-2.0
Classifier: Development Status :: 5 - Production/Stable
Classifier: License :: OSI Approved :: Apache Software License
Classifier: Programming Language :: Python :: 3.9
Classifier: Programming Language :: Python :: 3.10
Classifier: Programming Language :: Python :: 3.11
Classifier: Programming Language :: Python :: 3.12
Classifier: Programming Language :: Python :: Implementation :: CPython
Classifier: Programming Language :: Python :: Implementation :: PyPy
Classifier: Typing :: Typed
Requires-Python: >=3.9
Requires-Dist: pandas>=2.0.0
Requires-Dist: pyarrow>=10.0.0
Requires-Dist: grpcio>=1.59.3
Requires-Dist: grpcio-status>=1.59.3
Requires-Dist: googleapis-common-protos>=1.56.4
Requires-Dist: numpy>=1.21
